MANIFEST.in
README.rst
package.json
setup.cfg
setup.py
jslib/linkchecker.js
linkcheckerjs/__init__.py
linkcheckerjs/exc.py
linkcheckerjs/reader.py
linkcheckerjs/run.py
linkcheckerjs/thread.py
linkcheckerjs.egg-info/PKG-INFO
linkcheckerjs.egg-info/SOURCES.txt
linkcheckerjs.egg-info/dependency_links.txt
linkcheckerjs.egg-info/entry_points.txt
linkcheckerjs.egg-info/not-zip-safe
linkcheckerjs.egg-info/requires.txt
linkcheckerjs.egg-info/top_level.txt
linkcheckerjs/checker/__init__.py
linkcheckerjs/checker/phantomjs.py
linkcheckerjs/checker/requestspy.py
linkcheckerjs/checker/utils.py
tests/__init__.py