Metadata-Version: 1.1
Name: linkcheckerjs
Version: 0.1
Summary: Check links and resources in web page or full website
Home-page: Check links and resources in web page or full website
Author: Aurélien Matouillot
Author-email: a.matouillot@gmail.com
License: MIT
Keywords: checker,link,website,validation,crawler
Platform: UNKNOWN
Classifier: Programming Language :: Python
Classifier: Programming Language :: Python :: 2.6
Classifier: Programming Language :: Python :: 2.7
Classifier: Programming Language :: JavaScript
Classifier: Topic :: Internet :: WWW/HTTP :: Site Management :: Link Checking
Classifier: Intended Audience :: Developers
Classifier: License :: OSI Approved :: MIT License
